headline_analyzer/__init__.py
headline_analyzer/analyze_headline.py
headline_analyzer/analyze_headline_test.py
headline_analyzer/good-headline.py
headline_analyzer/goodheadlines/headlinebank.py
headline_analyzer/inference/__init__.py
headline_analyzer/inference/infer.py
headline_analyzer/inference/infer_test.py
headline_analyzer/stats/__init__.py
headline_analyzer/stats/count_characters.py
headline_analyzer/stats/count_characters_test.py
headline_analyzer/stats/count_words.py
headline_analyzer/stats/get_headline_stats.py
headline_analyzer/utils/__init__.py
headline_analyzer/utils/pretty_print.py
headline_analyzer/wordbank/__init__.py
headline_analyzer/wordbank/calculate_wordbank_percentage.py
headline_analyzer/wordbank/calculate_wordbank_percentage_test.py
headline_analyzer/wordbank/power_words.py
headline_analyzer/wordbank/tag_from_wordbanks.py
headline_analyzer/wordbank/tag_from_wordbanks_test.py
headline_analyzer/wordbank/tag_word.py
headline_analyzer/wordbank/tokenize.py
headline_analyzer/wordbank/tokenize_test.py
headline_analyzer/wordbank/uncommon_words.py
headline_analyzer/wordbank/wordbank.py
headline_analyzer-0.1.0.dist-info/WHEEL
headline_analyzer-0.1.0.dist-info/METADATA
headline_analyzer-0.1.0.dist-info/RECORD
