Metadata-Version: 2.1
Name: headline-analyzer
Version: 0.1.0
Summary: Analyze headlines for optimising conversion rate
License: MIT
Author: Nivrith
Author-email: nivrith.mandayam@gmail.com
Requires-Python: >=3.9,<4.0
Classifier: License :: OSI Approved :: MIT License
Classifier: Programming Language :: Python :: 3
Classifier: Programming Language :: Python :: 3.10
Classifier: Programming Language :: Python :: 3.9
